Metadata-Version: 2.1
Name: instructure-scraper
Version: 1.0.1
Summary: Instructure scraper
Home-page: UNKNOWN
Author: DataKund
Author-email: datakund@gmail.com
License: Apache License 2.0
Platform: UNKNOWN
License-File: LICENSE
